mcp_data_check/__init__.py
mcp_data_check/eval_methods.py
mcp_data_check/evaluator.py
mcp_data_check/run_eval.py
mcp_data_check-0.4.1.dist-info/METADATA
mcp_data_check-0.4.1.dist-info/WHEEL
mcp_data_check-0.4.1.dist-info/entry_points.txt
mcp_data_check-0.4.1.dist-info/licenses/LICENSE
mcp_data_check-0.4.1.dist-info/RECORD
