Metadata-Version: 2.4
Name: mcp-data-check
Version: 0.4.1
Summary: Evaluate MCP server accuracy against known questions and answers
Project-URL: Homepage, https://github.com/GSA-TTS/mcp-data-check
Project-URL: Repository, https://github.com/GSA-TTS/mcp-data-check
Project-URL: Issues, https://github.com/GSA-TTS/mcp-data-check/issues
Author-email: mark-aronson <marksaronson@gmail.com>
License: MIT
License-File: LICENSE
Keywords: anthropic,claude,evaluation,mcp,testing
Classifier: Development Status :: 4 - Beta
Classifier: Intended Audience :: Developers
Classifier: License :: OSI Approved :: MIT License
Classifier: Programming Language :: Python :: 3
Classifier: Programming Language :: Python :: 3.10
Classifier: Programming Language :: Python :: 3.11
Classifier: Programming Language :: Python :: 3.12
Classifier: Programming Language :: Python :: 3.13
Requires-Python: >=3.10
Requires-Dist: anthropic>=0.40.0
Requires-Dist: python-dotenv>=1.0.0
Provides-Extra: dev
Requires-Dist: pytest>=8.0.0; extra == 'dev'
Requires-Dist: twine>=5.0.0; extra == 'dev'
